{
    "name": "Hyena-class Droid Bomber",
    "xws": "hyenaclassdroidbomber",
    "size": "Small",
    "dial": [
        "1TW",
        "1BR",
        "1FW",
        "1NR",
        "1YW",
        "2ER",
        "2TB",
        "2BW",
        "2FB",
        "2NW",
        "2YB",
        "2RR",
        "2KR",
        "3TW",
        "3FB",
        "3YW",
        "4FW",
        "5FB"
    ],
    "faction": "Separatist Alliance",
    "stats": [
        {
            "arc": "Front Arc",
            "type": "attack",
            "value": 2
        },
        {
            "type": "agility",
            "value": 2
        },
        {
            "type": "hull",
            "value": 5
        }
    ],
    "actions": [
        {
            "difficulty": "White",
            "type": "Calculate"
        },
        {
            "difficulty": "White",
            "type": "Lock"
        },
        {
            "difficulty": "White",
            "type": "Barrel Roll",
            "linked": {
                "difficulty": "Red",
                "type": "Lock"
            }
        },
        {
            "difficulty": "Red",
            "type": "Reload"
        }
    ],
    "pilots": [
        {
            "name": "Techno Union Bomber",
            "initiative": 1,
            "limited": 0,
            "xws": "technounionbomber",
            "shipAbility": {
                "name": "Networked Calculations",
                "text": "While you defend or perform an attack, you may spend 1 calculate token from a friendly ship at range 0-1 to change 1 [Focus] result to an [Evade] or [Hit] result."
            },
            "hyperspace": false
        },
        {
            "name": "Bombardment Drone",
            "caption": "Time on Target",
            "limited": 3,
            "initiative": 3,
            "xws": "bombardmentdrone",
            "shipAbility": {
                "name": "Networked Calculations",
                "text": "While you defend or perform an attack, you may spend 1 calculate token from a friendly ship at range 0-1 to change 1 [Focus] result to an [Evade] or [Hit] result."
            },
            "ability": "If you would drop a device, you may launch that device instead, using the same template.",
            "image": "https://images-cdn.fantasyflightgames.com/filer_public/c8/3c/c83c098d-1a87-4f08-bcad-ad4cd9c8a00c/swz41_hyena-class-bomber.png",
            "hyperspace": false
        },
        {
            "name": "DBS-404",
            "xws": "dbs404",
            "initiative": 4,
            "limited": 1,
            "shipAbility": {
                "name": "Networked Calculations",
                "text": "While you defend or perform an attack, you may spend 1 calculate token from a friendly ship at range 0-1 to change 1 [Focus] result to an [Evade] or [Hit] result."
            },
            "hyperspace": false
        }
    ]
}
