{
  "name": "Quadrijet Transfer Spacetug",
  "size": "Small",
  "dial": [
    "1AR",
    "1DR",
    "1TW",
    "1BW",
    "1FW",
    "1NW",
    "1YW",
    "2SR",
    "2LR",
    "2TW",
    "2BB",
    "2FB",
    "2NB",
    "2YW",
    "2PR",
    "3BW",
    "3FB",
    "3NW"
  ],
  "faction": "Scum and Villainy",
  "stats": [
    {
      "arc": "Front Arc",
      "type": "attack",
      "value": 2
    },
    {
      "type": "agility",
      "value": 2
    },
    {
      "type": "hull",
      "value": 5
    }
  ],
  "ability": {
    "name": "Spacetug Tractor Array",
    "text": "Action: Choose a ship in your [Front Arc] at tange 1. That ship gains 1 tractor token, or 2 tractor tokens if it is in you [Bullseye Arc] at range 1."
  },
  "pilots": [
    {
      "name": "Constable Zuvio",
      "caption": "Missing Sheriff of Nima Outpost",
      "initiative": 4,
      "unique": true,
      "ability": "If you would drop a device, you may launch it using a [1 [Straight]] template instead.",
      "image": "https://i.imgur.com/7a7O9wm.jpg"
    },
    {
      "name": "Jakku Gunrunner",
      "initiative": 1,
      "unique": false,
      "text": "The Quadrijet transfer spacetug, commonly called a \"Quadjumper\" is nimble in space and atmosphere alike, making it populate among both smugglers and explorers.",
      "image": "https://i.imgur.com/HT0F6Yv.png"
    },
    {
      "name": "Sarco Plank",
      "caption": "The Scavenger",
      "initiative": 2,
      "unique": true,
      "ability": "While you defend, you may treat your agility value as equal to the speed of the maneuver you executed this round.",
      "image": "https://i.imgur.com/vCOYuiJ.jpg"
    },
    {
      "name": "Unkar Plutt",
      "caption": "Miserly Portion Master",
      "initiative": 2,
      "unique": true,
      "ability": "At the start of the Engagement Phase, if there are one or more other ships at range 0, you and each other ship at range 0 gain 1 tractor token.",
      "image": "https://i.imgur.com/VCf87Ha.png"
    }
  ]
}